res_facenet/__init__.py
res_facenet/models.py
res_facenet-0.0.5.dist-info/LICENSE
res_facenet-0.0.5.dist-info/METADATA
res_facenet-0.0.5.dist-info/WHEEL
res_facenet-0.0.5.dist-info/top_level.txt
res_facenet-0.0.5.dist-info/RECORD
