Metadata-Version: 2.1
Name: res-facenet
Version: 0.0.5
Summary: This model has been trained on VGGv2 and tested on LFW with 92% accuracy. The pretrained model can be accessed on res_facenet.model_921 or res_facenet.model_920
Home-page: https://github.com/khrlimam/res-facenet
Author: Khairul Imam
Author-email: ki65559@gmail.com
License: UNKNOWN
Platform: UNKNOWN
Classifier: Programming Language :: Python :: 3
Classifier: License :: OSI Approved :: MIT License
Classifier: Operating System :: OS Independent
Requires-Dist: torch
Requires-Dist: torchvision
